__init__.py
rand_sn/__init__.py
rand_sn/__main__.py
rand_sn/batch.py
rand_sn/config.py
rand_sn/full_cycle_random.py
rand_sn/l_f_s_r.py
rand_sn/main.py
rand_sn-1.0.0.dist-info/LICENSE.txt
rand_sn-1.0.0.dist-info/METADATA
rand_sn-1.0.0.dist-info/WHEEL
rand_sn-1.0.0.dist-info/entry_points.txt
rand_sn-1.0.0.dist-info/top_level.txt
rand_sn-1.0.0.dist-info/RECORD
