Metadata-Version: 2.1
Name: rand-sn
Version: 1.0.0
Summary: rand-sn is a versatile Python tool designed for generating randomized serial numbers along with their corresponding barcodes and QR codes, facilitating secure labeling, efficient scanning, and enhanced inventory management while preserving operational confidentiality.
Author-email: Peter JOHN Matecsa <matecsaj@gmail.com>
License: MIT License
Project-URL: homepage, https://github.com/matecsaj/rand_sn
Project-URL: issues, https://github.com/matecsaj/rand_sn/issues
Project-URL: repository, https://github.com/matecsaj/rand_sn
Keywords: barcode,QR code,inventory-management,serial-numbers
Classifier: Programming Language :: Python :: 3
Classifier: License :: OSI Approved :: MIT License
Classifier: Operating System :: OS Independent
Requires-Python: >=3.8
License-File: LICENSE.txt
Requires-Dist: python-barcode
Requires-Dist: qrcode[pil]
